README.rst
setup.py
cloudify_dsl_parser.egg-info/PKG-INFO
cloudify_dsl_parser.egg-info/SOURCES.txt
cloudify_dsl_parser.egg-info/dependency_links.txt
cloudify_dsl_parser.egg-info/not-zip-safe
cloudify_dsl_parser.egg-info/requires.txt
cloudify_dsl_parser.egg-info/top_level.txt
dsl_parser/__init__.py
dsl_parser/constants.py
dsl_parser/exceptions.py
dsl_parser/functions.py
dsl_parser/holder.py
dsl_parser/models.py
dsl_parser/multi_instance.py
dsl_parser/parser.py
dsl_parser/rel_graph.py
dsl_parser/scan.py
dsl_parser/tasks.py
dsl_parser/utils.py
dsl_parser/version.py
dsl_parser/yaml_loader.py
dsl_parser/elements/__init__.py
dsl_parser/elements/blueprint.py
dsl_parser/elements/data_types.py
dsl_parser/elements/imports.py
dsl_parser/elements/misc.py
dsl_parser/elements/node_templates.py
dsl_parser/elements/node_types.py
dsl_parser/elements/operation.py
dsl_parser/elements/plugins.py
dsl_parser/elements/policies.py
dsl_parser/elements/relationships.py
dsl_parser/elements/scalable.py
dsl_parser/elements/types.py
dsl_parser/elements/version.py
dsl_parser/elements/workflows.py
dsl_parser/framework/__init__.py
dsl_parser/framework/elements.py
dsl_parser/framework/parser.py
dsl_parser/framework/requirements.py
dsl_parser/import_resolver/__init__.py
dsl_parser/import_resolver/abstract_import_resolver.py
dsl_parser/import_resolver/default_import_resolver.py
dsl_parser/interfaces/__init__.py
dsl_parser/interfaces/constants.py
dsl_parser/interfaces/interfaces_merger.py
dsl_parser/interfaces/interfaces_parser.py
dsl_parser/interfaces/operation_merger.py
dsl_parser/interfaces/utils.py