Metadata-Version: 1.0
Name: cloudify-dsl-parser
Version: 4.3.1
Summary: Cloudify DSL parser
Home-page: UNKNOWN
Author: Gigaspaces
Author-email: cosmo-admin@gigaspaces.com
License: LICENSE
Platform: UNKNOWN
